CBingfaBianchengShizhan/README.md
CBingfaBianchengShizhan/__init__.py
CBingfaBianchengShizhan/__main__.py
CBingfaBianchengShizhan/file.epub
CBingfaBianchengShizhan/index.html
CBingfaBianchengShizhan/css/__init__.py
CBingfaBianchengShizhan/css/annotations.css
CBingfaBianchengShizhan/css/main.css
CBingfaBianchengShizhan/css/normalize.css
CBingfaBianchengShizhan/css/popup.css
CBingfaBianchengShizhan/font/__init__.py
CBingfaBianchengShizhan/font/fontello.eot
CBingfaBianchengShizhan/font/fontello.svg
CBingfaBianchengShizhan/font/fontello.ttf
CBingfaBianchengShizhan/font/fontello.woff
CBingfaBianchengShizhan/img/__init__.py
CBingfaBianchengShizhan/img/annotator-glyph-sprite.png
CBingfaBianchengShizhan/img/annotator-icon-sprite.png
CBingfaBianchengShizhan/img/apple-touch-icon.png
CBingfaBianchengShizhan/img/cancelfullscreen.png
CBingfaBianchengShizhan/img/close.png
CBingfaBianchengShizhan/img/fullscreen.png
CBingfaBianchengShizhan/img/loader.gif
CBingfaBianchengShizhan/img/menu-icon.png
CBingfaBianchengShizhan/img/save.png
CBingfaBianchengShizhan/img/saved.png
CBingfaBianchengShizhan/img/settings-s.png
CBingfaBianchengShizhan/img/settings.png
CBingfaBianchengShizhan/img/star.png
CBingfaBianchengShizhan/js/__init__.py
CBingfaBianchengShizhan/js/epub.js
CBingfaBianchengShizhan/js/epub.min.js
CBingfaBianchengShizhan/js/epub.min.map
CBingfaBianchengShizhan/js/hooks.min.js
CBingfaBianchengShizhan/js/hooks.min.map
CBingfaBianchengShizhan/js/reader.js
CBingfaBianchengShizhan/js/reader.js.map
CBingfaBianchengShizhan/js/reader.min.js
CBingfaBianchengShizhan/js/reader.min.map
CBingfaBianchengShizhan/js/hooks/__init__.py
CBingfaBianchengShizhan/js/hooks/extensions/__init__.py
CBingfaBianchengShizhan/js/hooks/extensions/highlight.js
CBingfaBianchengShizhan/js/libs/__init__.py
CBingfaBianchengShizhan/js/libs/jquery.min.js
CBingfaBianchengShizhan/js/libs/localforage.min.js
CBingfaBianchengShizhan/js/libs/screenfull.js
CBingfaBianchengShizhan/js/libs/screenfull.min.js
c_bingfa_biancheng_shizhan-2024.3.1.0.dist-info/METADATA
c_bingfa_biancheng_shizhan-2024.3.1.0.dist-info/WHEEL
c_bingfa_biancheng_shizhan-2024.3.1.0.dist-info/entry_points.txt
c_bingfa_biancheng_shizhan-2024.3.1.0.dist-info/top_level.txt
c_bingfa_biancheng_shizhan-2024.3.1.0.dist-info/RECORD
